RailsFenggeZhinan/README.md
RailsFenggeZhinan/__init__.py
RailsFenggeZhinan/__main__.py
RailsFenggeZhinan/file.epub
RailsFenggeZhinan/index.html
RailsFenggeZhinan/css/__init__.py
RailsFenggeZhinan/css/annotations.css
RailsFenggeZhinan/css/main.css
RailsFenggeZhinan/css/normalize.css
RailsFenggeZhinan/css/popup.css
RailsFenggeZhinan/font/__init__.py
RailsFenggeZhinan/font/fontello.eot
RailsFenggeZhinan/font/fontello.svg
RailsFenggeZhinan/font/fontello.ttf
RailsFenggeZhinan/font/fontello.woff
RailsFenggeZhinan/img/__init__.py
RailsFenggeZhinan/img/annotator-glyph-sprite.png
RailsFenggeZhinan/img/annotator-icon-sprite.png
RailsFenggeZhinan/img/apple-touch-icon.png
RailsFenggeZhinan/img/cancelfullscreen.png
RailsFenggeZhinan/img/close.png
RailsFenggeZhinan/img/fullscreen.png
RailsFenggeZhinan/img/loader.gif
RailsFenggeZhinan/img/menu-icon.png
RailsFenggeZhinan/img/save.png
RailsFenggeZhinan/img/saved.png
RailsFenggeZhinan/img/settings-s.png
RailsFenggeZhinan/img/settings.png
RailsFenggeZhinan/img/star.png
RailsFenggeZhinan/js/__init__.py
RailsFenggeZhinan/js/epub.js
RailsFenggeZhinan/js/epub.min.js
RailsFenggeZhinan/js/epub.min.map
RailsFenggeZhinan/js/hooks.min.js
RailsFenggeZhinan/js/hooks.min.map
RailsFenggeZhinan/js/reader.js
RailsFenggeZhinan/js/reader.js.map
RailsFenggeZhinan/js/reader.min.js
RailsFenggeZhinan/js/reader.min.map
RailsFenggeZhinan/js/hooks/__init__.py
RailsFenggeZhinan/js/hooks/extensions/__init__.py
RailsFenggeZhinan/js/hooks/extensions/highlight.js
RailsFenggeZhinan/js/libs/__init__.py
RailsFenggeZhinan/js/libs/jquery.min.js
RailsFenggeZhinan/js/libs/localforage.min.js
RailsFenggeZhinan/js/libs/screenfull.js
RailsFenggeZhinan/js/libs/screenfull.min.js
RailsFenggeZhinan/js/libs/zip.min.js
RailsFenggeZhinan/js/plugins/__init__.py
RailsFenggeZhinan/js/plugins/hypothesis.js
RailsFenggeZhinan/js/plugins/search.js
rails_fengge_zhinan-2024.3.2.0.dist-info/METADATA
rails_fengge_zhinan-2024.3.2.0.dist-info/WHEEL
rails_fengge_zhinan-2024.3.2.0.dist-info/entry_points.txt
rails_fengge_zhinan-2024.3.2.0.dist-info/top_level.txt
rails_fengge_zhinan-2024.3.2.0.dist-info/RECORD
